worldmeter
