Metadata-Version: 1.0
Name: worldmeter
Version: 0.2.1
Summary: stats for the world
Home-page: https://github.com/OpenJarbas/worldmeter
Author: jarbasAI
Author-email: jarbasai@mailfence.com
License: MIT
Platform: UNKNOWN
